loro-1.10.3.dist-info/METADATA
loro-1.10.3.dist-info/WHEEL
loro-1.10.3.dist-info/licenses/LICENSE
loro/__init__.py
loro/__init__.pyi
loro/loro.cpython-310-darwin.so
loro/py.typed
loro-1.10.3.dist-info/RECORD
