Metadata-Version: 2.4
Name: loro
Version: 1.10.3
Classifier: Programming Language :: Rust
Classifier: Programming Language :: Python :: Implementation :: CPython
Classifier: Programming Language :: Python :: Implementation :: PyPy
License-File: LICENSE
Summary: Python bindings for [Loro](https://loro.dev)
Keywords: local-first,CRDT,loro
Author-email: leon7hao <lz@loro.dev>
Requires-Python: >=3.8
Project-URL: Homepage, https://loro.dev
Project-URL: Repository, https://github.com/loro-dev/loro-py
